{
  "type": "AdaptiveCard",
  "body": [
    {
      "type": "RichTextBox",
      "inlines": [
        {
          "type": "TextRun",
          "text": "Інформація про тебе",
          "weight": "bolder"
        }
      ]
    },
    {
      "type": "RichTextBox",
      "inlines": [
        {
          "type": "TextRun",
          "text": "Прізвище:  ",
          "weight": "bolder"
        },
        {
          "type": "TextRun",
          "text": "LINK"
        }
      ]
    },
    {
      "type": "RichTextBox",
      "inlines": [
        {
          "type": "TextRun",
          "text": "Ім'я:  ",
          "weight": "bolder"
        },
        {
          "type": "TextRun",
          "text": "LINK"
        }
      ]
    },
    {
      "type": "RichTextBox",
      "inlines": [
        {
          "type": "TextRun",
          "text": "Email:  ",
          "weight": "bolder"
        },
        {
          "type": "TextRun",
          "text": "LINK"
        }
      ]
    },
    {
      "type": "RichTextBox",
      "inlines": [
        {
          "type": "TextRun",
          "text": "В компаніі з:  ",
          "weight": "bolder"
        },
        {
          "type": "TextRun",
          "text": "LINK"
        }
      ]
    }
  ],
  "actions": [
    {
      "type": "Action.Execute",
      "title": "Ок",
      "verb": "managerMenu",
      "fallback": "Action.Submit"
    }
  ],
  "minHeight": "200px",
  "keyword": "checkPersonalData",
  "dynamic": true,
  "shouldCareerUpdate": false
}
